odoo/addons/stock_packaging_usability/README.rst
odoo/addons/stock_packaging_usability/__init__.py
odoo/addons/stock_packaging_usability/__manifest__.py
odoo/addons/stock_packaging_usability/i18n/fr.po
odoo/addons/stock_packaging_usability/i18n/it.po
odoo/addons/stock_packaging_usability/i18n/stock_packaging_usability.pot
odoo/addons/stock_packaging_usability/models/__init__.py
odoo/addons/stock_packaging_usability/models/stock_move_line.py
odoo/addons/stock_packaging_usability/readme/CONFIGURE.rst
odoo/addons/stock_packaging_usability/readme/CONTRIBUTORS.rst
odoo/addons/stock_packaging_usability/readme/DESCRIPTION.rst
odoo/addons/stock_packaging_usability/static/description/icon.png
odoo/addons/stock_packaging_usability/static/description/index.html
odoo/addons/stock_packaging_usability/views/stock_move_line.xml
odoo14_addon_stock_packaging_usability-14.0.1.0.1.dev10.dist-info/METADATA
odoo14_addon_stock_packaging_usability-14.0.1.0.1.dev10.dist-info/WHEEL
odoo14_addon_stock_packaging_usability-14.0.1.0.1.dev10.dist-info/top_level.txt
odoo14_addon_stock_packaging_usability-14.0.1.0.1.dev10.dist-info/RECORD
